{"batter_id":650968,"full_name":"Yohel Pozo","team":"STL","position":"C","bats":"R","headshot_url":"https://img.mlbstatic.com/mlb-photos/image/upload/d_people:generic:headshot:67:current.png/w_213,q_auto:best/v1/people/650968/headshot/67/current","height_display":"5' 11\"","height_inches":71,"weight_lbs":201,"age":28,"pa":168,"ab":160,"hits":37,"doubles":8,"triples":0,"home_runs":5,"rbi":19,"walks":7,"strikeouts":22,"hbp":0,"ba":0.231,"obp":0.262,"slg":0.375,"ops":0.637,"avg_launch_speed":87.7,"hard_hit_rate":35.3,"barrel_rate":2.2,"sweet_spot_rate":29.5,"avg_launch_angle":17.8,"xba":0.246,"xslg":0.357,"xwoba":0.276,"chase_rate":48.1,"whiff_rate":19.8,"career_ab":234,"career_hr":6,"career_hbp":0,"career_ab_per_hr":39.0,"abs_since_last_hr":23,"abs_since_last_hbp":160,"due_for_status":"COLD STREAK","due_for_ratio":0.59,"thicc_boy_index":10.95,"plate_discipline_score":58.74,"plate_discipline_grade":"C"}