{"batter_id":677800,"full_name":"Wilyer Abreu","team":"BOS","position":"RF","bats":"L","headshot_url":"https://img.mlbstatic.com/mlb-photos/image/upload/d_people:generic:headshot:67:current.png/w_213,q_auto:best/v1/people/677800/headshot/67/current","height_display":"5' 10\"","height_inches":70,"weight_lbs":215,"age":26,"pa":417,"ab":373,"hits":92,"doubles":17,"triples":0,"home_runs":22,"rbi":69,"walks":40,"strikeouts":101,"hbp":0,"ba":0.247,"obp":0.317,"slg":0.469,"ops":0.786,"avg_launch_speed":90.8,"hard_hit_rate":44.9,"barrel_rate":12.3,"sweet_spot_rate":31.9,"avg_launch_angle":23.0,"xba":0.243,"xslg":0.475,"xwoba":0.335,"chase_rate":29.0,"whiff_rate":24.0,"career_ab":848,"career_hr":39,"career_hbp":3,"career_ab_per_hr":21.74,"abs_since_last_hr":21,"abs_since_last_hbp":373,"due_for_status":"ON PACE","due_for_ratio":0.966,"thicc_boy_index":57.21,"plate_discipline_score":65.18,"plate_discipline_grade":"B"}