{"batter_id":676694,"full_name":"Jake Meyers","team":"HOU","position":"CF","bats":"R","headshot_url":"https://img.mlbstatic.com/mlb-photos/image/upload/d_people:generic:headshot:67:current.png/w_213,q_auto:best/v1/people/676694/headshot/67/current","height_display":"6' 0\"","height_inches":72,"weight_lbs":200,"age":29,"pa":381,"ab":343,"hits":100,"doubles":15,"triples":2,"home_runs":3,"rbi":24,"walks":31,"strikeouts":67,"hbp":3,"ba":0.292,"obp":0.354,"slg":0.373,"ops":0.727,"avg_launch_speed":88.1,"hard_hit_rate":38.9,"barrel_rate":5.0,"sweet_spot_rate":34.6,"avg_launch_angle":9.8,"xba":0.269,"xslg":0.403,"xwoba":0.325,"chase_rate":23.7,"whiff_rate":21.2,"career_ab":1409,"career_hr":33,"career_hbp":24,"career_ab_per_hr":42.7,"abs_since_last_hr":207,"abs_since_last_hbp":10,"due_for_status":"OVERDUE","due_for_ratio":4.848,"thicc_boy_index":25.0,"plate_discipline_score":68.96,"plate_discipline_grade":"B"}