{"batter_id":686217,"full_name":"Sal Frelick","team":"MIL","position":"RF","bats":"L","headshot_url":"https://img.mlbstatic.com/mlb-photos/image/upload/d_people:generic:headshot:67:current.png/w_213,q_auto:best/v1/people/686217/headshot/67/current","height_display":"5' 9\"","height_inches":69,"weight_lbs":191,"age":25,"pa":594,"ab":528,"hits":152,"doubles":20,"triples":3,"home_runs":12,"rbi":63,"walks":47,"strikeouts":80,"hbp":7,"ba":0.288,"obp":0.351,"slg":0.405,"ops":0.756,"avg_launch_speed":85.5,"hard_hit_rate":27.4,"barrel_rate":3.1,"sweet_spot_rate":30.7,"avg_launch_angle":12.1,"xba":0.255,"xslg":0.339,"xwoba":0.299,"chase_rate":26.3,"whiff_rate":12.8,"career_ab":1194,"career_hr":17,"career_hbp":12,"career_ab_per_hr":70.24,"abs_since_last_hr":27,"abs_since_last_hbp":186,"due_for_status":"COLD STREAK","due_for_ratio":0.384,"thicc_boy_index":16.23,"plate_discipline_score":70.5,"plate_discipline_grade":"B"}