{"batter_id":680779,"full_name":"Henry Davis","team":"PIT","position":"C","bats":"R","headshot_url":"https://img.mlbstatic.com/mlb-photos/image/upload/d_people:generic:headshot:67:current.png/w_213,q_auto:best/v1/people/680779/headshot/67/current","height_display":"5' 11\"","height_inches":71,"weight_lbs":225,"age":26,"pa":283,"ab":252,"hits":42,"doubles":7,"triples":0,"home_runs":7,"rbi":22,"walks":18,"strikeouts":76,"hbp":5,"ba":0.167,"obp":0.234,"slg":0.278,"ops":0.512,"avg_launch_speed":88.6,"hard_hit_rate":37.4,"barrel_rate":11.5,"sweet_spot_rate":33.0,"avg_launch_angle":23.3,"xba":0.213,"xslg":0.389,"xwoba":0.293,"chase_rate":34.5,"whiff_rate":28.9,"career_ab":581,"career_hr":15,"career_hbp":10,"career_ab_per_hr":38.73,"abs_since_last_hr":0,"abs_since_last_hbp":64,"due_for_status":"COLD STREAK","due_for_ratio":0.0,"thicc_boy_index":51.11,"plate_discipline_score":61.24,"plate_discipline_grade":"B"}