{"batter_id":660271,"full_name":"Shohei Ohtani","team":"LAD","position":"TWP","bats":"L","headshot_url":"https://img.mlbstatic.com/mlb-photos/image/upload/d_people:generic:headshot:67:current.png/w_213,q_auto:best/v1/people/660271/headshot/67/current","height_display":"6' 4\"","height_inches":76,"weight_lbs":210,"age":31,"pa":727,"ab":611,"hits":172,"doubles":25,"triples":9,"home_runs":55,"rbi":102,"walks":109,"strikeouts":187,"hbp":3,"ba":0.282,"obp":0.392,"slg":0.622,"ops":1.014,"avg_launch_speed":94.9,"hard_hit_rate":58.7,"barrel_rate":23.5,"sweet_spot_rate":35.9,"avg_launch_angle":15.0,"xba":0.274,"xslg":0.649,"xwoba":0.425,"chase_rate":26.0,"whiff_rate":33.4,"career_ab":3730,"career_hr":280,"career_hbp":25,"career_ab_per_hr":13.32,"abs_since_last_hr":0,"abs_since_last_hbp":316,"due_for_status":"COLD STREAK","due_for_ratio":0.0,"thicc_boy_index":111.9,"plate_discipline_score":63.42,"plate_discipline_grade":"B"}