{"batter_id":669397,"full_name":"Nick Allen","team":"HOU","position":"SS","bats":"R","headshot_url":"https://img.mlbstatic.com/mlb-photos/image/upload/d_people:generic:headshot:67:current.png/w_213,q_auto:best/v1/people/669397/headshot/67/current","height_display":"5' 7\"","height_inches":67,"weight_lbs":166,"age":27,"pa":416,"ab":371,"hits":82,"doubles":11,"triples":0,"home_runs":0,"rbi":22,"walks":31,"strikeouts":99,"hbp":3,"ba":0.221,"obp":0.284,"slg":0.251,"ops":0.535,"avg_launch_speed":84.8,"hard_hit_rate":21.6,"barrel_rate":0.0,"sweet_spot_rate":29.3,"avg_launch_angle":13.3,"xba":0.22,"xslg":0.267,"xwoba":0.252,"chase_rate":25.8,"whiff_rate":21.5,"career_ab":1070,"career_hr":9,"career_hbp":5,"career_ab_per_hr":118.89,"abs_since_last_hr":371,"abs_since_last_hbp":213,"due_for_status":"OVERDUE","due_for_ratio":3.121,"thicc_boy_index":0.0,"plate_discipline_score":66.94,"plate_discipline_grade":"B"}