{"batter_id":664034,"full_name":"Ty France","team":"SD","position":"1B","bats":"R","headshot_url":"https://img.mlbstatic.com/mlb-photos/image/upload/d_people:generic:headshot:67:current.png/w_213,q_auto:best/v1/people/664034/headshot/67/current","height_display":"5' 10\"","height_inches":70,"weight_lbs":215,"age":31,"pa":490,"ab":444,"hits":114,"doubles":25,"triples":0,"home_runs":7,"rbi":52,"walks":22,"strikeouts":83,"hbp":21,"ba":0.257,"obp":0.32,"slg":0.36,"ops":0.68,"avg_launch_speed":89.5,"hard_hit_rate":44.2,"barrel_rate":7.7,"sweet_spot_rate":35.2,"avg_launch_angle":10.5,"xba":0.259,"xslg":0.425,"xwoba":0.328,"chase_rate":31.3,"whiff_rate":21.3,"career_ab":2957,"career_hr":81,"career_hbp":126,"career_ab_per_hr":36.51,"abs_since_last_hr":31,"abs_since_last_hbp":49,"due_for_status":"ON PACE","due_for_ratio":0.849,"thicc_boy_index":35.81,"plate_discipline_score":66.0,"plate_discipline_grade":"B"}