{"batter_id":608070,"full_name":"Jos\u00e9 Enrique Ram\u00edrez","team":"CLE","position":"3B","bats":"S","headshot_url":"https://img.mlbstatic.com/mlb-photos/image/upload/d_people:generic:headshot:67:current.png/w_213,q_auto:best/v1/people/608070/headshot/67/current","height_display":"5' 8\"","height_inches":68,"weight_lbs":190,"age":33,"pa":22,"ab":21,"hits":3,"doubles":2,"triples":0,"home_runs":0,"rbi":3,"walks":1,"strikeouts":5,"hbp":0,"ba":0.143,"obp":0.182,"slg":0.238,"ops":0.42,"avg_launch_speed":84.2,"hard_hit_rate":25.0,"barrel_rate":6.3,"sweet_spot_rate":31.3,"avg_launch_angle":27.4,"xba":0.232,"xslg":0.303,"xwoba":0.254,"career_ab":21,"career_hr":0,"career_hbp":0,"career_ab_per_hr":0,"abs_since_last_hr":0,"abs_since_last_hbp":0,"due_for_status":"COLD STREAK","due_for_ratio":0,"thicc_boy_index":0,"chase_rate":30,"whiff_rate":25,"plate_discipline_score":55.23,"plate_discipline_grade":"C","oil_profile":{"career_bob_pct":2.0,"regime_stats":{"cheap":{"bb":0,"barrels":0,"bob_pct":0},"normal":{"bb":99,"barrels":2,"bob_pct":2.0},"expensive":{"bb":0,"barrels":0,"bob_pct":0}},"oil_boost_index":0.0,"crisis_bob_pct":10.0,"badges":[],"dominant_regime":"normal"},"mercury_profile":{"retro_barrel_rate":null,"direct_barrel_rate":2.0,"retro_diff":null,"retro_bb":0,"direct_bb":99,"badges":[]}}